lmpy/__init__.py
lmpy/_version.py
lmpy/matrix.py
lmpy/point.py
lmpy/species_list.py
lmpy/tree.py
lmpy/data_preparation/__init__.py
lmpy/data_preparation/build_grid.py
lmpy/data_preparation/layer_encoder.py
lmpy/data_preparation/occurrence_splitter.py
lmpy/data_preparation/tree_encoder.py
lmpy/data_wrangling/__init__.py
lmpy/data_wrangling/base.py
lmpy/data_wrangling/factory.py
lmpy/data_wrangling/common/__init__.py
lmpy/data_wrangling/common/accepted_name_wrangler.py
lmpy/data_wrangling/matrix/__init__.py
lmpy/data_wrangling/matrix/accepted_name_wrangler.py
lmpy/data_wrangling/matrix/base.py
lmpy/data_wrangling/matrix/match_species_list_wrangler.py
lmpy/data_wrangling/matrix/match_tree_wrangler.py
lmpy/data_wrangling/matrix/purge_empty_slices_wrangler.py
lmpy/data_wrangling/matrix/subset_reorder_slices_wrangler.py
lmpy/data_wrangling/occurrence/__init__.py
lmpy/data_wrangling/occurrence/accepted_name_wrangler.py
lmpy/data_wrangling/occurrence/attribute_filter_wrangler.py
lmpy/data_wrangling/occurrence/attribute_modifier_wrangler.py
lmpy/data_wrangling/occurrence/base.py
lmpy/data_wrangling/occurrence/bounding_box_wrangler.py
lmpy/data_wrangling/occurrence/common_format_wrangler.py
lmpy/data_wrangling/occurrence/coordinate_conversion_wrangler.py
lmpy/data_wrangling/occurrence/decimal_precision_wrangler.py
lmpy/data_wrangling/occurrence/disjoint_geometries_wrangler.py
lmpy/data_wrangling/occurrence/intersect_geometries_wrangler.py
lmpy/data_wrangling/occurrence/match_species_list_wrangler.py
lmpy/data_wrangling/occurrence/minimum_points_wrangler.py
lmpy/data_wrangling/occurrence/spatial_index_wrangler.py
lmpy/data_wrangling/occurrence/unique_localities_wrangler.py
lmpy/data_wrangling/species_list/__init__.py
lmpy/data_wrangling/species_list/accepted_name_wrangler.py
lmpy/data_wrangling/species_list/base.py
lmpy/data_wrangling/species_list/intersect_species_list_wrangler.py
lmpy/data_wrangling/species_list/match_matrix_wrangler.py
specify_lmpy-3.1.21.dist-info/LICENSE
specify_lmpy-3.1.21.dist-info/METADATA
specify_lmpy-3.1.21.dist-info/WHEEL
specify_lmpy-3.1.21.dist-info/entry_points.txt
specify_lmpy-3.1.21.dist-info/top_level.txt
specify_lmpy-3.1.21.dist-info/RECORD
