Metadata-Version: 2.1
Name: specify-lmpy
Version: 3.1.21
Summary: Package of commonly used and shared Lifemapper objects and tools
Home-page: https://github.com/specifysystems/lmpy
Author: Specify Systems Lifemapper Team
Author-email: cjgrady@ku.edu
License: GNU GENERAL PUBLIC LICENSE
Project-URL: Bug Tracker, https://github.com/specifysystems/lmpy/issues
Classifier: Development Status :: 5 - Production/Stable
Classifier: Programming Language :: Python :: 3
Classifier: Programming Language :: Python :: 3.6
Classifier: Programming Language :: Python :: 3.7
Classifier: Programming Language :: Python :: 3.8
Classifier: Programming Language :: Python :: 3.9
Classifier: Programming Language :: Python :: 3.10
Classifier: License :: OSI Approved :: GNU General Public License v3 (GPLv3)
Classifier: Operating System :: OS Independent
Classifier: Topic :: Documentation :: Sphinx
Classifier: Topic :: Scientific/Engineering
Classifier: Topic :: Software Development :: Libraries :: Python Modules
Requires-Python: >=3.6
License-File: LICENSE
Requires-Dist: defusedxml
Requires-Dist: dendropy
Requires-Dist: numpy
Requires-Dist: gdal
Requires-Dist: matplotlib
Requires-Dist: requests
Requires-Dist: rtree
